gitwise/__init__.py
gitwise/config.py
gitwise/exceptions.py
gitwise/prompts.py
gitwise/security.py
gitwise/cli/__init__.py
gitwise/cli/add.py
gitwise/cli/commit_config.py
gitwise/cli/init.py
gitwise/cli/merge.py
gitwise/cli/standards.py
gitwise/core/__init__.py
gitwise/core/git_manager.py
gitwise/features/__init__.py
gitwise/features/add.py
gitwise/features/base.py
gitwise/features/branch.py
gitwise/features/changelog.py
gitwise/features/commit.py
gitwise/features/commit_rules.py
gitwise/features/context.py
gitwise/features/pr.py
gitwise/features/pr_enhancements.py
gitwise/features/pr_templates.py
gitwise/features/push.py
gitwise/features/smart_merge/__init__.py
gitwise/features/smart_merge/analyzer.py
gitwise/features/smart_merge/explainer.py
gitwise/features/smart_merge/merge_controller.py
gitwise/features/smart_merge/message_generator.py
gitwise/features/smart_merge/models.py
gitwise/features/smart_merge/resolver.py
gitwise/llm/__init__.py
gitwise/llm/model_presets.py
gitwise/llm/ollama.py
gitwise/llm/online.py
gitwise/llm/router.py
gitwise/llm/models/__init__.py
gitwise/llm/models/gemini_models.py
gitwise/llm/providers/__init__.py
gitwise/llm/providers/anthropic_provider.py
gitwise/llm/providers/base.py
gitwise/llm/providers/gemini_provider.py
gitwise/llm/providers/openai_provider.py
gitwise/llm/providers/openrouter_provider.py
gitwise/templates/commit_message.md
gitwise/templates/pr_description.md
gitwise/ui/__init__.py
gitwise/ui/components.py
pygitwise-0.2.0.dist-info/licenses/LICENSE
pygitwise-0.2.0.dist-info/METADATA
pygitwise-0.2.0.dist-info/WHEEL
pygitwise-0.2.0.dist-info/entry_points.txt
pygitwise-0.2.0.dist-info/top_level.txt
pygitwise-0.2.0.dist-info/RECORD
