Metadata-Version: 2.4
Name: pygitwise
Version: 0.2.0
Summary: AI-powered Git assistant with privacy-first design. Choose between local (Ollama/Offline) or cloud AI to automate commits, PRs, and changelogs.
Home-page: https://github.com/PayasPandey11/gitwise
Author: Payas Pandey
Author-email: rpayaspandey@gmail.com
License: AGPL-3.0-or-later OR Commercial
Project-URL: Source, https://github.com/PayasPandey11/gitwise
Project-URL: Documentation, https://github.com/PayasPandey11/gitwise/blob/main/README.md
Project-URL: Issues, https://github.com/PayasPandey11/gitwise/issues
Classifier: Development Status :: 4 - Beta
Classifier: Intended Audience :: Developers
Classifier: License :: OSI Approved :: GNU Affero General Public License v3 or later (AGPLv3+)
Classifier: Operating System :: OS Independent
Classifier: Programming Language :: Python :: 3
Classifier: Programming Language :: Python :: 3.8
Classifier: Programming Language :: Python :: 3.9
Classifier: Programming Language :: Python :: 3.10
Classifier: Programming Language :: Python :: 3.11
Classifier: Programming Language :: Python :: 3.12
Classifier: Topic :: Software Development :: Version Control :: Git
Classifier: Topic :: Utilities
Requires-Python: >=3.8
License-File: LICENSE
Requires-Dist: typer>=0.9.0
Requires-Dist: rich>=13.0.0
Requires-Dist: requests>=2.0.0
Requires-Dist: jinja2
Requires-Dist: openai>=1.0.0
Requires-Dist: keyring>=24.0.0
Provides-Extra: dev
Requires-Dist: pytest; extra == "dev"
Requires-Dist: pytest-cov; extra == "dev"
Requires-Dist: flake8; extra == "dev"
Requires-Dist: black; extra == "dev"
Requires-Dist: isort; extra == "dev"
Requires-Dist: mypy; extra == "dev"
Provides-Extra: cloud-llms
Requires-Dist: google-generativeai>=0.3.0; extra == "cloud-llms"
Requires-Dist: openai>=1.0.0; extra == "cloud-llms"
Requires-Dist: anthropic>=0.20.0; extra == "cloud-llms"
Provides-Extra: all-llms
Requires-Dist: google-generativeai>=0.3.0; extra == "all-llms"
Requires-Dist: anthropic>=0.20.0; extra == "all-llms"
Dynamic: author
Dynamic: author-email
Dynamic: classifier
Dynamic: home-page
Dynamic: license
Dynamic: license-file
Dynamic: project-url
Dynamic: provides-extra
Dynamic: requires-dist
Dynamic: requires-python
Dynamic: summary
